{
    "AX": {
        "error": 0.0005362966756613116,
        "fit": "exponential",
        "references": [
            {
                "exclude": "ok",
                "record_id": "a-01-A-714",
                "uuid": "16459b1e-83d7-41ba-bad9-46b5e8c9e7c8"
            },
            {
                "exclude": "ok",
                "record_id": "a-01-A-715",
                "uuid": "da811f12-46e7-468b-991d-88da362ee413"
            },
            {
                "exclude": "ok",
                "record_id": "a-01-A-716",
                "uuid": "c9a92848-fd98-451f-9c0e-ad2c27efb8a2"
            },
            {
                "exclude": "ok",
                "record_id": "a-01-A-720",
                "uuid": "b3ebf604-8690-467b-976d-2ea6c8acf155"
            },
            {
                "exclude": "ok",
                "record_id": "a-01-A-721",
                "uuid": "934250e7-2f84-4f15-9fdb-1b7ccd0c7fd2"
            },
            {
                "exclude": "ok",
                "record_id": "a-01-A-722",
                "uuid": "cdb9350e-f1f4-488d-abdc-e599bf6cca33"
            },
            {
                "exclude": "ok",
                "record_id": "a-01-A-723",
                "uuid": "8e8661e2-a459-4907-b1e4-4d33417e5c53"
            },
            {
                "exclude": "ok",
                "record_id": "a-01-A-724",
                "uuid": "4dfa2e15-58ba-4670-8369-c6d5d8687c68"
            },
            {
                "exclude": "ok",
                "record_id": "a-01-A-725",
                "uuid": "c1097a75-2d44-4229-9cdd-dab370c83a79"
            }
        ],
        "reviewed": true,
        "value": 1.0010858139720693
    },
    "CDD": {
        "error": 0.0009075459080116276,
        "fit": "Bracketing Interpolate",
        "references": [
            {
                "exclude": "ok",
                "record_id": "a-01-A-714",
                "uuid": "16459b1e-83d7-41ba-bad9-46b5e8c9e7c8"
            },
            {
                "exclude": "ok",
                "record_id": "a-01-A-715",
                "uuid": "da811f12-46e7-468b-991d-88da362ee413"
            },
            {
                "exclude": "ok",
                "record_id": "a-01-A-716",
                "uuid": "c9a92848-fd98-451f-9c0e-ad2c27efb8a2"
            },
            {
                "exclude": "ok",
                "record_id": "a-01-A-720",
                "uuid": "b3ebf604-8690-467b-976d-2ea6c8acf155"
            },
            {
                "exclude": "ok",
                "record_id": "a-01-A-721",
                "uuid": "934250e7-2f84-4f15-9fdb-1b7ccd0c7fd2"
            },
            {
                "exclude": "ok",
                "record_id": "a-01-A-722",
                "uuid": "cdb9350e-f1f4-488d-abdc-e599bf6cca33"
            },
            {
                "exclude": "ok",
                "record_id": "a-01-A-723",
                "uuid": "8e8661e2-a459-4907-b1e4-4d33417e5c53"
            },
            {
                "exclude": "ok",
                "record_id": "a-01-A-724",
                "uuid": "4dfa2e15-58ba-4670-8369-c6d5d8687c68"
            },
            {
                "exclude": "ok",
                "record_id": "a-01-A-725",
                "uuid": "c1097a75-2d44-4229-9cdd-dab370c83a79"
            }
        ],
        "reviewed": true,
        "value": 1.0121049735591234
    },
    "H1": {
        "error": 0.0,
        "fit": "default",
        "references": [],
        "value": 1.0
    },
    "H2": {
        "error": 0.0,
        "fit": "default",
        "references": [],
        "value": 1.0
    },
    "L1": {
        "error": 0.001089350062425685,
        "fit": "exponential",
        "references": [
            {
                "exclude": "ok",
                "record_id": "a-01-A-714",
                "uuid": "16459b1e-83d7-41ba-bad9-46b5e8c9e7c8"
            },
            {
                "exclude": "ok",
                "record_id": "a-01-A-715",
                "uuid": "da811f12-46e7-468b-991d-88da362ee413"
            },
            {
                "exclude": "ok",
                "record_id": "a-01-A-716",
                "uuid": "c9a92848-fd98-451f-9c0e-ad2c27efb8a2"
            },
            {
                "exclude": "ok",
                "record_id": "a-01-A-720",
                "uuid": "b3ebf604-8690-467b-976d-2ea6c8acf155"
            },
            {
                "exclude": "ok",
                "record_id": "a-01-A-721",
                "uuid": "934250e7-2f84-4f15-9fdb-1b7ccd0c7fd2"
            },
            {
                "exclude": "ok",
                "record_id": "a-01-A-722",
                "uuid": "cdb9350e-f1f4-488d-abdc-e599bf6cca33"
            },
            {
                "exclude": "ok",
                "record_id": "a-01-A-723",
                "uuid": "8e8661e2-a459-4907-b1e4-4d33417e5c53"
            },
            {
                "exclude": "ok",
                "record_id": "a-01-A-724",
                "uuid": "4dfa2e15-58ba-4670-8369-c6d5d8687c68"
            },
            {
                "exclude": "ok",
                "record_id": "a-01-A-725",
                "uuid": "c1097a75-2d44-4229-9cdd-dab370c83a79"
            }
        ],
        "reviewed": true,
        "value": 1.0022043236871256
    },
    "L2": {
        "error": 0.001655358600877964,
        "fit": "exponential",
        "references": [
            {
                "exclude": "ok",
                "record_id": "a-01-A-714",
                "uuid": "16459b1e-83d7-41ba-bad9-46b5e8c9e7c8"
            },
            {
                "exclude": "ok",
                "record_id": "a-01-A-715",
                "uuid": "da811f12-46e7-468b-991d-88da362ee413"
            },
            {
                "exclude": "ok",
                "record_id": "a-01-A-716",
                "uuid": "c9a92848-fd98-451f-9c0e-ad2c27efb8a2"
            },
            {
                "exclude": "ok",
                "record_id": "a-01-A-720",
                "uuid": "b3ebf604-8690-467b-976d-2ea6c8acf155"
            },
            {
                "exclude": "ok",
                "record_id": "a-01-A-721",
                "uuid": "934250e7-2f84-4f15-9fdb-1b7ccd0c7fd2"
            },
            {
                "exclude": "ok",
                "record_id": "a-01-A-722",
                "uuid": "cdb9350e-f1f4-488d-abdc-e599bf6cca33"
            },
            {
                "exclude": "ok",
                "record_id": "a-01-A-723",
                "uuid": "8e8661e2-a459-4907-b1e4-4d33417e5c53"
            },
            {
                "exclude": "ok",
                "record_id": "a-01-A-724",
                "uuid": "4dfa2e15-58ba-4670-8369-c6d5d8687c68"
            },
            {
                "exclude": "ok",
                "record_id": "a-01-A-725",
                "uuid": "c1097a75-2d44-4229-9cdd-dab370c83a79"
            }
        ],
        "reviewed": true,
        "value": 1.0033477460419238
    }
}